microbert/__init__.py
microbert/model.py
microbert/predict.py
microbert/tokenizer.py
microbert/train.py
microbert/utils.py
microbert/data/prepare_imdb_json.py
microbert-0.0.2.dist-info/licenses/LICENSE
microbert-0.0.2.dist-info/METADATA
microbert-0.0.2.dist-info/WHEEL
microbert-0.0.2.dist-info/top_level.txt
microbert-0.0.2.dist-info/RECORD
